qual_gis/__init__.py
qual_gis/common.py
qual_gis/qual_gis.py
qual_gis-0.0.1.dist-info/LICENSE
qual_gis-0.0.1.dist-info/METADATA
qual_gis-0.0.1.dist-info/WHEEL
qual_gis-0.0.1.dist-info/entry_points.txt
qual_gis-0.0.1.dist-info/top_level.txt
qual_gis-0.0.1.dist-info/RECORD
